{
    "video_start_time": "2024-07-18 12:52:40.811726",
    "video_end_time": "2024-07-18 12:52:50.834544",
    "clicks": [
        {
            "x": 864,
            "y": 50,
            "time": "2024-07-18 12:52:53.599374",
            "action": "Action.ADD_POINT"
        },
        {
            "x": 863,
            "y": 30,
            "time": "2024-07-18 12:52:54.874005",
            "action": "Action.ADD_POINT"
        },
        {
            "x": 460,
            "y": 308,
            "time": "2024-07-18 12:52:56.533974",
            "action": "Action.ADD_POINT"
        },
        {
            "x": 477,
            "y": 323,
            "time": "2024-07-18 12:52:57.552465",
            "action": "Action.ADD_POINT"
        },
        {
            "x": 799,
            "y": 575,
            "time": "2024-07-18 12:52:59.269236",
            "action": "Action.ADD_POINT"
        },
        {
            "x": 814,
            "y": 591,
            "time": "2024-07-18 12:53:01.874888",
            "action": "Action.ADD_POINT"
        },
        {
            "x": 697,
            "y": 793,
            "time": "2024-07-18 12:53:04.018305",
            "action": "Action.ADD_POINT"
        },
        {
            "x": 676,
            "y": 798,
            "time": "2024-07-18 12:53:05.231468",
            "action": "Action.ADD_POINT"
        }
    ],
    "saved_points": [
        {
            "x": 864,
            "y": 50
        },
        {
            "x": 863,
            "y": 30
        },
        {
            "x": 460,
            "y": 308
        },
        {
            "x": 477,
            "y": 323
        },
        {
            "x": 799,
            "y": 575
        },
        {
            "x": 814,
            "y": 591
        },
        {
            "x": 697,
            "y": 793
        },
        {
            "x": 676,
            "y": 798
        }
    ]
}